LICENSE
MANIFEST.in
README.rst
requirements.txt
setup.py
critic/__init__.py
critic/admin.py
critic/managers.py
critic/models.py
critic/modules.py
critic/settings.py
critic/tests.py
critic/urls.py
critic/utils.py
critic/views.py
critic/fixtures/test_data.json
critic/templates/critic/placeholder.txt
critic/templates/critic/render.html
critic/templatetags/__init__.py
critic/templatetags/critic_tags.py
django_critic.egg-info/PKG-INFO
django_critic.egg-info/SOURCES.txt
django_critic.egg-info/dependency_links.txt
django_critic.egg-info/top_level.txt
doc_src/Makefile
doc_src/conf.py
doc_src/getting_started.rst
doc_src/index.rst
doc_src/installation.rst
doc_src/make.bat
doc_src/_build/doctrees/environment.pickle
doc_src/_build/doctrees/getting_started.doctree
doc_src/_build/doctrees/index.doctree
doc_src/_build/doctrees/installation.doctree
doc_src/_build/doctrees/reference/api.doctree
doc_src/_build/doctrees/reference/index.doctree
doc_src/_build/doctrees/reference/settings.doctree
doc_src/_build/doctrees/reference/template_tags.doctree
doc_src/_static/breadcrumb_background.png
doc_src/_static/default.css
doc_src/_static/documentation.png
doc_src/_static/header_sm_mid.png
doc_src/_static/scrn1.png
doc_src/_static/scrn2.png
doc_src/_static/searchfield_leftcap.png
doc_src/_static/searchfield_repeat.png
doc_src/_static/searchfield_rightcap.png
doc_src/_static/title_background.png
doc_src/_static/toc.js
doc_src/_static/triangle_closed.png
doc_src/_static/triangle_left.png
doc_src/_static/triangle_open.png
doc_src/_templates/layout.html
doc_src/reference/api.rst
doc_src/reference/index.rst
doc_src/reference/settings.rst
doc_src/reference/template_tags.rst
docs/.buildinfo
docs/genindex.html
docs/getting_started.html
docs/index.html
docs/installation.html
docs/objects.inv
docs/search.html
docs/searchindex.js
docs/_sources/getting_started.txt
docs/_sources/index.txt
docs/_sources/installation.txt
docs/_sources/reference/api.txt
docs/_sources/reference/index.txt
docs/_sources/reference/settings.txt
docs/_sources/reference/template_tags.txt
docs/_static/basic.css
docs/_static/breadcrumb_background.png
docs/_static/default.css
