Metadata-Version: 1.0
Name: django-critic
Version: 0.2.4
Summary: A rating application.
Home-page: http://github.com/josesoa/django-critic
Author: Jose Soares
Author-email: jsoares@washingtontimes.com
License: UNKNOWN
Platform: UNKNOWN
Classifier: Development Status :: 4 - Beta
Classifier: Environment :: Web Environment
Classifier: Framework :: Django
Classifier: Intended Audience :: Developers
Classifier: License :: OSI Approved :: Apache Software License
Classifier: Programming Language :: Python
Classifier: Operating System :: OS Independent
